README.txt
bootstrap.py
buildout.cfg
charm.py
plonesite.cfg
setup.py
tests.py
./charm.py
charm.egg-info/PKG-INFO
charm.egg-info/SOURCES.txt
charm.egg-info/dependency_links.txt
charm.egg-info/entry_points.txt
charm.egg-info/requires.txt
charm.egg-info/top_level.txt
docs/CONTRIBUTORS.txt
docs/HISTORY.txt
docs/LICENSE.txt
html/README.txt
html/index.html
html/plone-logo-128-white-bg.png
html/sample.doc
html/sample.xls
html/2011/01/01/test-collapse/index.html
html/_sample/index.html
html/a/index.html
html/ac/index.html
html/condimentum/index.html
html/cursus/index.html
html/dis/index.html
html/fames/index.html
html/gravida/index.html
html/id/index.html
html/integer/index.html
html/libero/index.html
html/mi/index.html
html/mollis/index.html
html/nec/index.html
html/nulla/index.html
html/nullam/index.html
html/pede/index.html
html/phasellus/index.html
html/platea/index.html
html/porta/index.html
html/risus/index.html