Metadata-Version: 1.0
Name: charm
Version: 1.0b4
Summary: Import static websites on the file system into Plone.
Home-page: https://github.com/aclark4life/charm
Author: Alex Clark
Author-email: aclark@aclark.net
License: UNKNOWN
Platform: UNKNOWN
Classifier: Framework :: Buildout
Classifier: Framework :: Plone
